DESCRIPTION.rst
MANIFEST.in
README.rst
setup.py
hooktrigger/__init__.py
hooktrigger/__main__.py
hooktrigger/hooktrigger.py
hooktrigger.egg-info/PKG-INFO
hooktrigger.egg-info/SOURCES.txt
hooktrigger.egg-info/dependency_links.txt
hooktrigger.egg-info/entry_points.txt
hooktrigger.egg-info/top_level.txt