Metadata-Version: 1.1
Name: hooktrigger
Version: 0.1.3
Summary: Run shell commands when GitHub webhooks are fired
Home-page: https://github.com/NotBobTheBuilder/hook-trigger
Author: Jack Wearden
Author-email: jack@jackwearden.co.uk
License: MIT
Keywords: deployment
Platform: UNKNOWN
Classifier: Development Status :: 4 - Beta
Classifier: Intended Audience :: Developers
Classifier: Topic :: Software Development :: Build Tools
Classifier: License :: OSI Approved :: MIT License
Classifier: Programming Language :: Python :: 3.4
